README.rst
ez_setup.py
setup.py
imagebot/__init__.py
imagebot/__main__.py
imagebot/clear.py
imagebot/dbmanager.py
imagebot/env.py
imagebot/items.py
imagebot/main.py
imagebot/middleware.py
imagebot/monitor.py
imagebot/monitor_gtk.py
imagebot/monitor_tk.py
imagebot/pipelines.py
imagebot/settings.py
imagebot/settings_dev.py
imagebot/settings_release.py
imagebot/sort.py
imagebot/tables.sql
imagebot/version.py
imagebot.egg-info/PKG-INFO
imagebot.egg-info/SOURCES.txt
imagebot.egg-info/dependency_links.txt
imagebot.egg-info/entry_points.txt
imagebot.egg-info/requires.txt
imagebot.egg-info/top_level.txt
imagebot/spiders/__init__.py
imagebot/spiders/bot.py
imagebot/spiders/init.py