Metadata-Version: 1.1
Name: imagebot
Version: 1.2.1
Summary: A web bot to crawl websites and scrape images.
Home-page: http://pypi.python.org/pypi/imagebot/
Author: Amol Umrale
Author-email: babaiscool@gmail.com
License: UNKNOWN
Platform: UNKNOWN
Classifier: Development Status :: 4 - Beta
Classifier: Environment :: Console
Classifier: Framework :: Scrapy
Classifier: Framework :: Twisted
Classifier: License :: OSI Approved :: MIT License
Classifier: Natural Language :: English
Classifier: Operating System :: POSIX :: Linux
Classifier: Operating System :: Microsoft :: Windows
Classifier: Programming Language :: Python :: 2.7
Classifier: Topic :: Internet :: WWW/HTTP :: Indexing/Search
